README.md
setup.py
crimjustsimpy/Case.py
crimjustsimpy/CaseFactory.py
crimjustsimpy/Docket.py
crimjustsimpy/DocketFactory.py
crimjustsimpy/Experiment.py
crimjustsimpy/ExperimentData.py
crimjustsimpy/IdGen.py
crimjustsimpy/PleaBargainingAtRandom.py
crimjustsimpy/PleaBargainingStrategy.py
crimjustsimpy/RandomNormalBounded.py
crimjustsimpy/RandomPoissonBounded.py
crimjustsimpy/RandomScaledBetaProb.py
crimjustsimpy/Trial.py
crimjustsimpy/Visualization.py
crimjustsimpy/__init__.py
crimjustsimpy.egg-info/PKG-INFO
crimjustsimpy.egg-info/SOURCES.txt
crimjustsimpy.egg-info/dependency_links.txt
crimjustsimpy.egg-info/requires.txt
crimjustsimpy.egg-info/top_level.txt