Metadata-Version: 2.1
Name: crimjustsimpy
Version: 1.0.5
Summary: Tools for criminal just simulation
Home-page: https://github.com/mdraughn/crimjustsimpy
Author: Mark Draughn
Author-email: mark@windypundit.com
License: mit
Keywords: criminal justice model simulation
Platform: UNKNOWN
Classifier: Development Status :: 2 - Pre-Alpha
Classifier: Intended Audience :: Education
Classifier: Intended Audience :: Science/Research
Classifier: Programming Language :: Python :: 3
Classifier: License :: OSI Approved :: MIT License
Classifier: Operating System :: OS Independent
Requires-Python: >=3.3
